MANIFEST.in
README.rst
setup.py
filedata_ext/__init__.py
filedata_ext/constants.py
filedata_ext.egg-info/PKG-INFO
filedata_ext.egg-info/SOURCES.txt
filedata_ext.egg-info/dependency_links.txt
filedata_ext.egg-info/not-zip-safe
filedata_ext.egg-info/requires.txt
filedata_ext.egg-info/top_level.txt
filedata_ext/data_models/__init__.py
filedata_ext/data_models/file_info.py
filedata_ext/data_models/ocr.py
filedata_ext/services/__init__.py
filedata_ext/services/file_handler.py
filedata_ext/services/filedata_cache.py
filedata_ext/utils/__init__.py
filedata_ext/utils/video.py
requirements/test.txt
tests/__init__.py
tests/file_handler_test.py
tests/resources/example.docx
tests/resources/example.pdf
tests/resources/example.png